<?xml version="1.0" encoding="utf-8" ?>
<!--
-
- phpMyAdmin XML Dump
- version 2.11.8.1deb5+lenny1
- http://www.phpmyadmin.net
-
- Host: localhost
- Erstellungszeit: 18. September 2009 um 23:23
- Server Version: 5.0.67
- PHP-Version: 5.2.6-1+lenny3
-->

<!--
- Datenbank: 'ETS9'
- SELECT city, city_name, user, points, alliance, home, b_hangar FROM `city` Order by points desc limit 0,50
-->
<ETS9>
  <!-- Tabelle city -->
    <city>
        <city>2:73:3</city>
        <city_name>Vielen Danke an:</city_name>
        <user>Drizzt</user>
        <points>1759</points>
        <alliance>2Spieler-viele_Rekorde</alliance>
        <home>YES</home>
        <b_hangar>162</b_hangar>
    </city>
    <city>
        <city>2:34:10</city>
        <city_name>ALLES</city_name>
        <user>Haschiwu</user>
        <points>1731</points>
        <alliance>BuG</alliance>
        <home>YES</home>
        <b_hangar>151</b_hangar>
    </city>
    <city>
        <city>2:49:29</city>
        <city_name>HALLE / SAALE ROCKT</city_name>
        <user>Chiquita</user>
        <points>1655</points>
        <alliance>a4tw</alliance>
        <home>YES</home>
        <b_hangar>150</b_hangar>
    </city>
    <city>
        <city>2:95:22</city>
        <city_name>***Teutis Reich***</city_name>
        <user>heisererEber</user>
        <points>1626</points>
        <alliance>BIuG</alliance>
        <home>YES</home>
        <b_hangar>146</b_hangar>
    </city>
    <city>
        <city>2:73:2</city>
        <city_name>Nils aka Robbomat</city_name>
        <user>Drizzt</user>
        <points>1592</points>
        <alliance>2Spieler-viele_Rekorde</alliance>
        <home>NO</home>
        <b_hangar>161</b_hangar>
    </city>
    <city>
        <city>2:73:4</city>
        <city_name>ohne ihn waere</city_name>
        <user>Drizzt</user>
        <points>1589</points>
        <alliance>2Spieler-viele_Rekorde</alliance>
        <home>NO</home>
        <b_hangar>161</b_hangar>
    </city>
    <city>
        <city>2:74:4</city>
        <city_name>Tesserakt thx chucky</city_name>
        <user>Schattenwolf</user>
        <points>1588</points>
        <alliance>Votet_fuer_ETS</alliance>
        <home>YES</home>
        <b_hangar>142</b_hangar>
    </city>
    <city>
        <city>3:132:1</city>
        <city_name>-G-G-uxis Rul0rt</city_name>
        <user>Dave</user>
        <points>1565</points>
        <alliance>BuG</alliance>
        <home>YES</home>
        <b_hangar>165</b_hangar>
    </city>
    <city>
        <city>2:47:6</city>
        <city_name>Feldküche</city_name>
        <user>saite</user>
        <points>1563</points>
        <alliance>Armee</alliance>
        <home>YES</home>
        <b_hangar>148</b_hangar>
    </city>
    <city>
        <city>2:74:2</city>
        <city_name>das alles nicht</city_name>
        <user>Drizzt</user>
        <points>1556</points>
        <alliance>2Spieler-viele_Rekorde</alliance>
        <home>NO</home>
        <b_hangar>156</b_hangar>
    </city>
    <city>
        <city>3:32:19</city>
        <city_name>-</city_name>
        <user>Haschiwu</user>
        <points>1538</points>
        <alliance>BuG</alliance>
        <home>NO</home>
        <b_hangar>177</b_hangar>
    </city>
    <city>
        <city>3:45:3</city>
        <city_name>Blandy -G-G- THRUST</city_name>
        <user>Haschiwu</user>
        <points>1534</points>
        <alliance>BuG</alliance>
        <home>NO</home>
        <b_hangar>166</b_hangar>
    </city>
    <city>
        <city>2:73:5</city>
        <city_name>moeglich gewesen</city_name>
        <user>Drizzt</user>
        <points>1532</points>
        <alliance>2Spieler-viele_Rekorde</alliance>
        <home>NO</home>
        <b_hangar>157</b_hangar>
    </city>
    <city>
        <city>2:73:6</city>
        <city_name>desweiteren dank an </city_name>
        <user>Drizzt</user>
        <points>1531</points>
        <alliance>2Spieler-viele_Rekorde</alliance>
        <home>NO</home>
        <b_hangar>157</b_hangar>
    </city>
    <city>
        <city>3:132:3</city>
        <city_name>-G-G-</city_name>
        <user>Haschiwu</user>
        <points>1524</points>
        <alliance>BuG</alliance>
        <home>NO</home>
        <b_hangar>175</b_hangar>
    </city>
    <city>
        <city>3:127:1</city>
        <city_name>Walhall</city_name>
        <user>KnallHart</user>
        <points>1522</points>
        <alliance>-RBS-</alliance>
        <home>YES</home>
        <b_hangar>181</b_hangar>
    </city>
    <city>
        <city>2:34:9</city>
        <city_name>KEKSE</city_name>
        <user>Haschiwu</user>
        <points>1520</points>
        <alliance>BuG</alliance>
        <home>NO</home>
        <b_hangar>158</b_hangar>
    </city>
    <city>
        <city>3:148:11</city>
        <city_name>egal</city_name>
        <user>stargate</user>
        <points>1520</points>
        <alliance>-Vision-</alliance>
        <home>YES</home>
        <b_hangar>149</b_hangar>
    </city>
    <city>
        <city>2:94:9</city>
        <city_name>Krawall &amp; Remmidemmi</city_name>
        <user>HustenderMulch</user>
        <points>1518</points>
        <alliance>BuG</alliance>
        <home>YES</home>
        <b_hangar>151</b_hangar>
    </city>
    <city>
        <city>2:80:26</city>
        <city_name>Genju Slade</city_name>
        <user>Drizzt</user>
        <points>1518</points>
        <alliance>2Spieler-viele_Rekorde</alliance>
        <home>NO</home>
        <b_hangar>153</b_hangar>
    </city>
    <city>
        <city>2:77:21</city>
        <city_name>Naphtalin &amp; LENK !!</city_name>
        <user>Drizzt</user>
        <points>1513</points>
        <alliance>2Spieler-viele_Rekorde</alliance>
        <home>NO</home>
        <b_hangar>155</b_hangar>
    </city>
    <city>
        <city>3:132:4</city>
        <city_name>-G-G-</city_name>
        <user>Haschiwu</user>
        <points>1512</points>
        <alliance>BuG</alliance>
        <home>NO</home>
        <b_hangar>172</b_hangar>
    </city>
    <city>
        <city>2:60:5</city>
        <city_name>BLUNA fuers Leben</city_name>
        <user>Drizzt</user>
        <points>1509</points>
        <alliance>2Spieler-viele_Rekorde</alliance>
        <home>NO</home>
        <b_hangar>165</b_hangar>
    </city>
    <city>
        <city>2:36:16</city>
        <city_name>~~~~ UnPuShEd ~~~~</city_name>
        <user>MrKnister</user>
        <points>1508</points>
        <alliance>Zi_Vi_Sion</alliance>
        <home>YES</home>
        <b_hangar>171</b_hangar>
    </city>
    <city>
        <city>2:34:11</city>
        <city_name>MEINE</city_name>
        <user>Haschiwu</user>
        <points>1505</points>
        <alliance>BuG</alliance>
        <home>NO</home>
        <b_hangar>151</b_hangar>
    </city>
    <city>
        <city>3:45:4</city>
        <city_name>x3 Blandy -G-G-</city_name>
        <user>Haschiwu</user>
        <points>1505</points>
        <alliance>BuG</alliance>
        <home>NO</home>
        <b_hangar>166</b_hangar>
    </city>
    <city>
        <city>3:45:5</city>
        <city_name>x4 Blandy -G-G-</city_name>
        <user>Haschiwu</user>
        <points>1504</points>
        <alliance>BuG</alliance>
        <home>NO</home>
        <b_hangar>165</b_hangar>
    </city>
    <city>
        <city>3:3:14</city>
        <city_name>Slainté</city_name>
        <user>Avenger</user>
        <points>1495</points>
        <alliance>NbN</alliance>
        <home>YES</home>
        <b_hangar>145</b_hangar>
    </city>
    <city>
        <city>3:58:25</city>
        <city_name>Stadt</city_name>
        <user>Naka</user>
        <points>1486</points>
        <alliance>BuG</alliance>
        <home>YES</home>
        <b_hangar>187</b_hangar>
    </city>
    <city>
        <city>2:16:10</city>
        <city_name>Coruscant</city_name>
        <user>chriscross</user>
        <points>1478</points>
        <alliance>-RBS-</alliance>
        <home>YES</home>
        <b_hangar>154</b_hangar>
    </city>
    <city>
        <city>3:32:18</city>
        <city_name>-</city_name>
        <user>Haschiwu</user>
        <points>1471</points>
        <alliance>BuG</alliance>
        <home>NO</home>
        <b_hangar>173</b_hangar>
    </city>
    <city>
        <city>2:34:14</city>
        <city_name>KEKSE</city_name>
        <user>Haschiwu</user>
        <points>1470</points>
        <alliance>BuG</alliance>
        <home>NO</home>
        <b_hangar>156</b_hangar>
    </city>
    <city>
        <city>2:132:10</city>
        <city_name>hArdstYle</city_name>
        <user>electronic</user>
        <points>1470</points>
        <alliance>CoIS</alliance>
        <home>YES</home>
        <b_hangar>144</b_hangar>
    </city>
    <city>
        <city>2:58:2</city>
        <city_name>Bluna</city_name>
        <user>Drizzt</user>
        <points>1469</points>
        <alliance>2Spieler-viele_Rekorde</alliance>
        <home>NO</home>
        <b_hangar>148</b_hangar>
    </city>
    <city>
        <city>3:132:5</city>
        <city_name>-G-G-</city_name>
        <user>Haschiwu</user>
        <points>1466</points>
        <alliance>BuG</alliance>
        <home>NO</home>
        <b_hangar>161</b_hangar>
    </city>
    <city>
        <city>3:141:9</city>
        <city_name>-G-G-</city_name>
        <user>Valdez</user>
        <points>1463</points>
        <alliance>BuG</alliance>
        <home>YES</home>
        <b_hangar>121</b_hangar>
    </city>
    <city>
        <city>3:107:23</city>
        <city_name>Furlows</city_name>
        <user>Draks</user>
        <points>1449</points>
        <alliance>BIuG</alliance>
        <home>YES</home>
        <b_hangar>159</b_hangar>
    </city>
    <city>
        <city>3:103:29</city>
        <city_name>[S] Flieger u Kolos</city_name>
        <user>Davidoff</user>
        <points>1445</points>
        <alliance>BuG</alliance>
        <home>YES</home>
        <b_hangar>189</b_hangar>
    </city>
    <city>
        <city>2:19:17</city>
        <city_name>Klendathu</city_name>
        <user>JohnRico</user>
        <points>1440</points>
        <alliance>CoIS</alliance>
        <home>YES</home>
        <b_hangar>159</b_hangar>
    </city>
    <city>
        <city>3:101:12</city>
        <city_name>Darksite</city_name>
        <user>Rungal</user>
        <points>1439</points>
        <alliance>Armee</alliance>
        <home>YES</home>
        <b_hangar>153</b_hangar>
    </city>
    <city>
        <city>3:121:33</city>
        <city_name>Toplist verBuGt.. oO</city_name>
        <user>camel</user>
        <points>1439</points>
        <alliance>CoIS</alliance>
        <home>YES</home>
        <b_hangar>175</b_hangar>
    </city>
    <city>
        <city>2:47:24</city>
        <city_name>Neue Stadt</city_name>
        <user>Haschiwu</user>
        <points>1437</points>
        <alliance>BuG</alliance>
        <home>NO</home>
        <b_hangar>151</b_hangar>
    </city>
    <city>
        <city>4:15:33</city>
        <city_name>Bluna</city_name>
        <user>Drizzt</user>
        <points>1432</points>
        <alliance>2Spieler-viele_Rekorde</alliance>
        <home>NO</home>
        <b_hangar>145</b_hangar>
    </city>
    <city>
        <city>3:105:3</city>
        <city_name>kugelmugel</city_name>
        <user>langos</user>
        <points>1431</points>
        <alliance>-RBS-</alliance>
        <home>YES</home>
        <b_hangar>157</b_hangar>
    </city>
    <city>
        <city>2:101:32</city>
        <city_name>zanza</city_name>
        <user>kante</user>
        <points>1430</points>
        <alliance>AAW</alliance>
        <home>YES</home>
        <b_hangar>163</b_hangar>
    </city>
    <city>
        <city>2:83:8</city>
        <city_name>KoF-G Wolfman</city_name>
        <user>Chickenlilli</user>
        <points>1430</points>
        <alliance>i-leet</alliance>
        <home>YES</home>
        <b_hangar>141</b_hangar>
    </city>
    <city>
        <city>3:90:18</city>
        <city_name>[S]Kolo auf K3 ;o)</city_name>
        <user>Ulab</user>
        <points>1428</points>
        <alliance>AAW</alliance>
        <home>YES</home>
        <b_hangar>162</b_hangar>
    </city>
    <city>
        <city>2:142:9</city>
        <city_name>Bluna</city_name>
        <user>Drizzt</user>
        <points>1428</points>
        <alliance>2Spieler-viele_Rekorde</alliance>
        <home>NO</home>
        <b_hangar>147</b_hangar>
    </city>
    <city>
        <city>2:59:13</city>
        <city_name>Bluna</city_name>
        <user>Drizzt</user>
        <points>1426</points>
        <alliance>2Spieler-viele_Rekorde</alliance>
        <home>NO</home>
        <b_hangar>142</b_hangar>
    </city>
    <city>
        <city>2:131:7</city>
        <city_name>Bluna</city_name>
        <user>Drizzt</user>
        <points>1426</points>
        <alliance>2Spieler-viele_Rekorde</alliance>
        <home>NO</home>
        <b_hangar>145</b_hangar>
    </city>
</ETS9>