<?xml version="1.0" encoding="utf-8" ?>
<!--
-
- phpMyAdmin XML Dump
- version 2.11.8.1deb5+lenny8
- http://www.phpmyadmin.net
-
- Host: localhost
- Erstellungszeit: 17. Juli 2011 um 16:48
- Server Version: 5.0.51
- PHP-Version: 5.3.5-0.dotdeb.0
-->

<!--
- Datenbank: 'ETS9'
- SELECT tag, members, points FROM `alliances` Order by points desc limit 0,50
- vim: :
:%s/database name="[^"]*"/ETS9
:%s/\/database/\/ETS9
:%s/table name="\([^"]*\)"/\1
:%s/\/table/\/alliances
:%s/column name="\([^"]*\)"\(>[^<]*<\)\/column/\1\2\/\1
-->
    <ETS9>
        <!-- Tabelle alliances -->
        <alliances>
            <tag>SG33K</tag>
            <members>24</members>
            <points>247460</points>
        </alliances>
        <alliances>
            <tag>BuG</tag>
            <members>17</members>
            <points>199747</points>
        </alliances>
        <alliances>
            <tag>VisioN</tag>
            <members>38</members>
            <points>182992</points>
        </alliances>
        <alliances>
            <tag>WuH</tag>
            <members>20</members>
            <points>171252</points>
        </alliances>
        <alliances>
            <tag>GdS</tag>
            <members>19</members>
            <points>147915</points>
        </alliances>
        <alliances>
            <tag>IB</tag>
            <members>24</members>
            <points>112830</points>
        </alliances>
        <alliances>
            <tag>BKA</tag>
            <members>12</members>
            <points>78149</points>
        </alliances>
        <alliances>
            <tag>Frauenparkplatz</tag>
            <members>9</members>
            <points>69536</points>
        </alliances>
        <alliances>
            <tag>-FC-</tag>
            <members>11</members>
            <points>66916</points>
        </alliances>
        <alliances>
            <tag>TK</tag>
            <members>15</members>
            <points>66893</points>
        </alliances>
        <alliances>
            <tag>SG69K</tag>
            <members>12</members>
            <points>61969</points>
        </alliances>
        <alliances>
            <tag>Biug</tag>
            <members>13</members>
            <points>61464</points>
        </alliances>
        <alliances>
            <tag>hf</tag>
            <members>8</members>
            <points>58141</points>
        </alliances>
        <alliances>
            <tag>-BU-</tag>
            <members>8</members>
            <points>45985</points>
        </alliances>
        <alliances>
            <tag>MAD</tag>
            <members>7</members>
            <points>42265</points>
        </alliances>
        <alliances>
            <tag>WuM_3.5</tag>
            <members>4</members>
            <points>41483</points>
        </alliances>
        <alliances>
            <tag>dWfB</tag>
            <members>10</members>
            <points>37186</points>
        </alliances>
        <alliances>
            <tag>DF</tag>
            <members>5</members>
            <points>20884</points>
        </alliances>
        <alliances>
            <tag>Vendetta</tag>
            <members>2</members>
            <points>19465</points>
        </alliances>
        <alliances>
            <tag>Medaron</tag>
            <members>9</members>
            <points>18851</points>
        </alliances>
        <alliances>
            <tag>DKV</tag>
            <members>3</members>
            <points>16351</points>
        </alliances>
        <alliances>
            <tag>ANTIFArm</tag>
            <members>5</members>
            <points>14929</points>
        </alliances>
        <alliances>
            <tag>Umzugstrupp</tag>
            <members>4</members>
            <points>12936</points>
        </alliances>
        <alliances>
            <tag>KoF</tag>
            <members>4</members>
            <points>10246</points>
        </alliances>
        <alliances>
            <tag>BiOLAND</tag>
            <members>1</members>
            <points>8439</points>
        </alliances>
        <alliances>
            <tag>BSA</tag>
            <members>2</members>
            <points>7979</points>
        </alliances>
        <alliances>
            <tag>WoMD</tag>
            <members>1</members>
            <points>7023</points>
        </alliances>
        <alliances>
            <tag>HB</tag>
            <members>1</members>
            <points>6368</points>
        </alliances>
        <alliances>
            <tag>LuN</tag>
            <members>2</members>
            <points>5899</points>
        </alliances>
        <alliances>
            <tag>RU.HE</tag>
            <members>3</members>
            <points>5743</points>
        </alliances>
        <alliances>
            <tag>OPPES</tag>
            <members>3</members>
            <points>5639</points>
        </alliances>
        <alliances>
            <tag>KGS</tag>
            <members>2</members>
            <points>5415</points>
        </alliances>
        <alliances>
            <tag>NIN</tag>
            <members>1</members>
            <points>5404</points>
        </alliances>
        <alliances>
            <tag>Bro</tag>
            <members>1</members>
            <points>5296</points>
        </alliances>
        <alliances>
            <tag>WoK</tag>
            <members>1</members>
            <points>5287</points>
        </alliances>
        <alliances>
            <tag>-CHAOS-</tag>
            <members>1</members>
            <points>4971</points>
        </alliances>
        <alliances>
            <tag>SG.U</tag>
            <members>4</members>
            <points>3703</points>
        </alliances>
        <alliances>
            <tag>VADN</tag>
            <members>2</members>
            <points>3670</points>
        </alliances>
        <alliances>
            <tag>KoC</tag>
            <members>2</members>
            <points>2719</points>
        </alliances>
        <alliances>
            <tag>blub</tag>
            <members>1</members>
            <points>2363</points>
        </alliances>
        <alliances>
            <tag>HZ</tag>
            <members>1</members>
            <points>1939</points>
        </alliances>
        <alliances>
            <tag>EfE</tag>
            <members>1</members>
            <points>1695</points>
        </alliances>
        <alliances>
            <tag>DSA</tag>
            <members>1</members>
            <points>1495</points>
        </alliances>
        <alliances>
            <tag>I</tag>
            <members>1</members>
            <points>1399</points>
        </alliances>
        <alliances>
            <tag>exKGS</tag>
            <members>1</members>
            <points>1386</points>
        </alliances>
        <alliances>
            <tag>HAN</tag>
            <members>1</members>
            <points>1353</points>
        </alliances>
        <alliances>
            <tag>Troja</tag>
            <members>1</members>
            <points>1258</points>
        </alliances>
        <alliances>
            <tag>KgU</tag>
            <members>1</members>
            <points>1079</points>
        </alliances>
        <alliances>
            <tag>BORG</tag>
            <members>1</members>
            <points>1023</points>
        </alliances>
        <alliances>
            <tag>DSMDM</tag>
            <members>1</members>
            <points>1015</points>
        </alliances>
    </ETS9>


